aas_python_http_client/__init__.py
aas_python_http_client/api_client.py
aas_python_http_client/configuration.py
aas_python_http_client/rest.py
aas_python_http_client/util.py
aas_python_http_client/api/__init__.py
aas_python_http_client/api/aasx_file_server_api_api.py
aas_python_http_client/api/asset_administration_shell_api_api.py
aas_python_http_client/api/asset_administration_shell_basic_discovery_api_api.py
aas_python_http_client/api/asset_administration_shell_registry_api_api.py
aas_python_http_client/api/asset_administration_shell_repository_api_api.py
aas_python_http_client/api/concept_description_repository_api_api.py
aas_python_http_client/api/description_api_api.py
aas_python_http_client/api/serialization_api_api.py
aas_python_http_client/api/submodel_api_api.py
aas_python_http_client/api/submodel_registry_api_api.py
aas_python_http_client/api/submodel_repository_api_api.py
aas_python_http_client/models/__init__.py
aas_python_http_client/models/aas_submodel_elements.py
aas_python_http_client/models/abstract_lang_string.py
aas_python_http_client/models/administrative_information.py
aas_python_http_client/models/all_of_resource_content_type.py
aas_python_http_client/models/all_of_resource_path.py
aas_python_http_client/models/annotated_relationship_element.py
aas_python_http_client/models/annotated_relationship_element_metadata.py
aas_python_http_client/models/annotated_relationship_element_value.py
aas_python_http_client/models/asset_administration_shell.py
aas_python_http_client/models/asset_administration_shell_descriptor.py
aas_python_http_client/models/asset_information.py
aas_python_http_client/models/asset_kind.py
aas_python_http_client/models/assetinformation_thumbnail_body.py
aas_python_http_client/models/assetinformation_thumbnail_body1.py
aas_python_http_client/models/base_operation_result.py
aas_python_http_client/models/basic_event_element.py
aas_python_http_client/models/basic_event_element_metadata.py
aas_python_http_client-1.0.2.dist-info/LICENSE
aas_python_http_client-1.0.2.dist-info/METADATA
aas_python_http_client-1.0.2.dist-info/WHEEL
aas_python_http_client-1.0.2.dist-info/top_level.txt
aas_python_http_client-1.0.2.dist-info/RECORD
