Metadata-Version: 2.1
Name: aas-python-http-client
Version: 1.0.2
Summary: Python Client for DotAAS Part 2 | HTTP/REST | Entire API Collection
Home-page: https://github.com/rwth-iat/aas-python-http-client
Author-email: i.garmaev@iat.rwth-aachen.de
Keywords: Swagger,DotAAS Part 2 | HTTP/REST | Entire API Collection,AAS
Classifier: Programming Language :: Python :: 3
Classifier: License :: OSI Approved :: MIT License
Classifier: Operating System :: OS Independent
Requires-Python: >=3.9
License-File: LICENSE
Requires-Dist: urllib3>=1.15
Requires-Dist: six>=1.10
Requires-Dist: certifi
Requires-Dist: python-dateutil
Requires-Dist: basyx-python-sdk
